titanq/__init__.py
titanq/_client/__init__.py
titanq/_client/client.py
titanq/_client/model.py
titanq/_model/__init__.py
titanq/_model/constraints.py
titanq/_model/errors.py
titanq/_model/model.py
titanq/_model/numpy_util.py
titanq/_model/objective.py
titanq/_model/optimize_response.py
titanq/_model/variable.py
titanq/_storage/__init__.py
titanq/_storage/managed_storage.py
titanq/_storage/s3_storage.py
titanq/_storage/storage_client.py
titanq-6.0.0.dist-info/LICENSE.txt
titanq-6.0.0.dist-info/METADATA
titanq-6.0.0.dist-info/WHEEL
titanq-6.0.0.dist-info/top_level.txt
titanq-6.0.0.dist-info/RECORD
