Metadata-Version: 2.1
Name: titanq
Version: 6.0.0
Summary: The TitanQ SDK for python
Maintainer-email: InfinityQ <support@infinityq.tech>
License: Apache 2.0
Project-URL: Homepage, https://www.infinityq.tech
Project-URL: Documentation, https://docs.titanq.infinityq.io/quickstart/category/python-sdk
Keywords: titan,titanq,optimization,platform,infinity,infinityq
Classifier: Development Status :: 4 - Beta
Classifier: Intended Audience :: Developers
Classifier: Topic :: Scientific/Engineering
Classifier: License :: OSI Approved :: Apache Software License 
Classifier: Programming Language :: Python :: 3
Classifier: Programming Language :: Python :: 3.9
Classifier: Programming Language :: Python :: 3.10
Classifier: Programming Language :: Python :: 3.11
Requires-Python: >=3.9
License-File: LICENSE.txt
Requires-Dist: requests >=2.31.0
Requires-Dist: boto3 >=1.28.46
Requires-Dist: numpy >=1.23.4
Requires-Dist: pydantic >=2.5.3
